{
  "type": "FeatureCollection",
  "features": [
    {
      "type": "Feature",
      "properties": {
        "名称": "星巴克（保定雄安市民服务中心店）",
        "下载速度": "52.2 Mbps",
        "Speedtest 链接": "https://www.speedtest.net/my-result/i/4623865039",
        "评论 (@xhacker)": "周末人不太多，网速快。中间桌子有少量电源。",
        "厕所": "附近有公共厕所。",
        "marker-color": "#50C240",
        "marker-symbol": "cafe"
      },
      "geometry": {
        "type": "Point",
        "coordinates": [
          115.907,
          39.05
        ]
      }
    }
  ]
}
