{
  "type": "FeatureCollection",
  "features": [
    {
      "type": "Feature",
      "properties": {
        "名称": "咖世家咖啡（Costa Coffee）",
        "下载速度": "4.63 Mbps",
        "Speedtest 链接": "http://beta.speedtest.net/result/6381402353",
        "评论 (@cosmos53076)": "成都市中心位置，人少，网速还可以。",
        "marker-color": "#F3AE1A",
        "marker-symbol": "cafe"
      },
      "geometry": {
        "type": "Point",
        "coordinates": [
          104.068281,
          30.661270
        ]
      }
    },
    {
      "type": "Feature",
      "properties": {
        "名称": "漫咖啡(3号店)（Manne Coffee）",
        "下载速度": "10.43 Mbps",
        "Speedtest 链接": "http://beta.speedtest.net/result/6381848344",
        "评论 (@cosmos53076)": "高新区，网速很快，人很多",
        "marker-color": "#50C240",
        "marker-symbol": "cafe"
      },
      "geometry": {
        "type": "Point",
        "coordinates": [
          104.063417,
          30.549483
        ]
      }
    }
  ]
}
